{
  "generatedAt": "2026-05-20T17:36:26.537Z",
  "collections": [
    {
      "name": "users",
      "type": "auth",
      "apiRules": {
        "list": "id = @request.auth.id",
        "view": "id = @request.auth.id",
        "create": "",
        "update": "id = @request.auth.id",
        "delete": "id = @request.auth.id"
      },
      "fields": [
        {
          "name": "name",
          "type": "text",
          "required": false,
          "system": false
        },
        {
          "name": "avatar",
          "type": "file",
          "required": false,
          "system": false
        },
        {
          "name": "created",
          "type": "autodate",
          "required": false,
          "system": false,
          "autodateTriggers": ["onCreate"]
        },
        {
          "name": "updated",
          "type": "autodate",
          "required": false,
          "system": false,
          "autodateTriggers": ["onCreate", "onUpdate"]
        },
        {
          "name": "signature",
          "type": "text",
          "required": false,
          "system": false
        }
      ],
      "indexes": [
        "CREATE UNIQUE INDEX `idx_tokenKey__pb_users_auth_` ON `users` (`tokenKey`)",
        "CREATE UNIQUE INDEX `idx_email__pb_users_auth_` ON `users` (`email`) WHERE `email` != ''"
      ]
    },
    {
      "name": "devices",
      "type": "base",
      "apiRules": {
        "list": "@request.auth.id != ''",
        "view": "@request.auth.id != ''",
        "create": "@request.auth.id != ''",
        "update": "@request.auth.id != ''",
        "delete": "@request.auth.id != ''"
      },
      "fields": [
        {
          "name": "name",
          "type": "text",
          "required": true,
          "system": false
        },
        {
          "name": "department",
          "type": "text",
          "required": false,
          "system": false
        },
        {
          "name": "status",
          "type": "text",
          "required": true,
          "system": false
        },
        {
          "name": "unread_count",
          "type": "number",
          "required": false,
          "system": false
        },
        {
          "name": "created",
          "type": "autodate",
          "required": false,
          "system": false,
          "autodateTriggers": ["onCreate"]
        },
        {
          "name": "updated",
          "type": "autodate",
          "required": false,
          "system": false,
          "autodateTriggers": ["onCreate", "onUpdate"]
        },
        {
          "name": "instance_key",
          "type": "text",
          "required": false,
          "system": false
        }
      ],
      "indexes": [
        "CREATE UNIQUE INDEX `idx_devices_instance_key` ON `devices` (instance_key) WHERE instance_key != ''"
      ]
    },
    {
      "name": "messages",
      "type": "base",
      "apiRules": {
        "list": "@request.auth.id != ''",
        "view": "@request.auth.id != ''",
        "create": "@request.auth.id != ''",
        "update": "@request.auth.id != ''",
        "delete": "@request.auth.id != ''"
      },
      "fields": [
        {
          "name": "content",
          "type": "text",
          "required": true,
          "system": false
        },
        {
          "name": "device_id",
          "type": "relation",
          "required": false,
          "system": false,
          "collectionRef": "devices"
        },
        {
          "name": "sender_id",
          "type": "relation",
          "required": false,
          "system": false,
          "collectionRef": "users"
        },
        {
          "name": "is_read",
          "type": "bool",
          "required": false,
          "system": false
        },
        {
          "name": "created",
          "type": "autodate",
          "required": false,
          "system": false,
          "autodateTriggers": ["onCreate"]
        },
        {
          "name": "updated",
          "type": "autodate",
          "required": false,
          "system": false,
          "autodateTriggers": ["onCreate", "onUpdate"]
        },
        {
          "name": "remote_sender",
          "type": "text",
          "required": false,
          "system": false
        },
        {
          "name": "direction",
          "type": "select",
          "required": false,
          "system": false,
          "selectValues": ["inbound", "outbound"]
        }
      ],
      "indexes": []
    },
    {
      "name": "notes",
      "type": "base",
      "apiRules": {
        "list": "@request.auth.id != '' && user_id = @request.auth.id",
        "view": "@request.auth.id != '' && user_id = @request.auth.id",
        "create": "@request.auth.id != '' && user_id = @request.auth.id",
        "update": "@request.auth.id != '' && user_id = @request.auth.id",
        "delete": "@request.auth.id != '' && user_id = @request.auth.id"
      },
      "fields": [
        {
          "name": "title",
          "type": "text",
          "required": true,
          "system": false
        },
        {
          "name": "content",
          "type": "text",
          "required": true,
          "system": false
        },
        {
          "name": "user_id",
          "type": "relation",
          "required": true,
          "system": false,
          "collectionRef": "users"
        },
        {
          "name": "created",
          "type": "autodate",
          "required": false,
          "system": false,
          "autodateTriggers": ["onCreate"]
        },
        {
          "name": "updated",
          "type": "autodate",
          "required": false,
          "system": false,
          "autodateTriggers": ["onCreate", "onUpdate"]
        }
      ],
      "indexes": []
    }
  ]
}
